{
    "result_code": "SUCCESS",
    "error_msg": "",
    "alert_msg": "",
    "location_href": "",
    "location_replace": "",
    "custom_script": "",
    "total_cnt": 0,
    "data": "{  \"categoryCode\" : \"C0000017\",  \"categoryName\" : \"시럽\",  \"engCategoryName\" : \"Syrup\",  \"applyType1\" : \"02\",  \"applyType2\" : \"\",  \"level\" : \"1\",  \"categoryDesc\" : \"시럽 권장수량 : 숏(2) 톨(3) 그란데(4) 벤티(5)\",  \"categoryList\" : [ {    \"categoryCode\" : \"C0000064\",    \"categoryName\" : \"시럽 없이(선택)\",    \"engCategoryName\" : \"\",    \"applyType1\" : \"02\",    \"applyType2\" : \"01\",    \"level\" : \"2\",    \"categoryDesc\" : \"\",    \"maxQty\" : \"0\",    \"maxQtyMsg\" : \"\",    \"stdRecipeFlag\" : \"N\",    \"payType\" : \"01\",    \"customGrp\" : \"R\",    \"btnStatus\" : \"D\",    \"skuList\" : [ {      \"skuNo\" : \"4002090000204\",      \"skuName\" : \"클래식 시럽 없이\",      \"baseQty\" : \"0\",      \"stdRecipeFlag\" : \"N\",      \"calories\" : \"0\",      \"price\" : \"0\",      \"callingName\" : \"노 클래식\",      \"callingSeq\" : \"8701\",      \"payType\" : \"01\",      \"customGrp\" : \"R\",      \"btnStatus\" : \"D\",      \"markingName\" : \"/CS\",      \"markingSeq\" : \"8701\",      \"skuNameShort\" : \"클래식 시럽 없이\"    } ]  }, {    \"categoryCode\" : \"C0000050\",    \"categoryName\" : \"바닐라 시럽\",    \"engCategoryName\" : \"\",    \"applyType1\" : \"01\",    \"applyType2\" : \"02\",    \"level\" : \"2\",    \"categoryDesc\" : \"\",    \"maxQty\" : \"9\",    \"maxQtyMsg\" : \"\",    \"stdRecipeFlag\" : \"N\",    \"payType\" : \"01\",    \"customGrp\" : \"R\",    \"btnStatus\" : \"D\",    \"skuList\" : [ {      \"skuNo\" : \"4002090000024\",      \"skuName\" : \"바닐라 시럽\",      \"baseQty\" : \"0\",      \"stdRecipeFlag\" : \"N\",      \"calories\" : \"0\",      \"price\" : \"600\",      \"callingName\" : \"펌프 바닐라\",      \"callingSeq\" : \"8730\",      \"payType\" : \"01\",      \"customGrp\" : \"R\",      \"btnStatus\" : \"D\",      \"markingName\" : \"V\",      \"markingSeq\" : \"8730\",      \"skuNameShort\" : \"바닐라 시럽\"    } ]  }, {    \"categoryCode\" : \"C0000051\",    \"categoryName\" : \"헤이즐넛 시럽\",    \"engCategoryName\" : \"\",    \"applyType1\" : \"01\",    \"applyType2\" : \"02\",    \"level\" : \"2\",    \"categoryDesc\" : \"\",    \"maxQty\" : \"9\",    \"maxQtyMsg\" : \"\",    \"stdRecipeFlag\" : \"N\",    \"payType\" : \"01\",    \"customGrp\" : \"R\",    \"btnStatus\" : \"D\",    \"skuList\" : [ {      \"skuNo\" : \"4002090000026\",      \"skuName\" : \"헤이즐넛 시럽\",      \"baseQty\" : \"0\",      \"stdRecipeFlag\" : \"N\",      \"calories\" : \"0\",      \"price\" : \"600\",      \"callingName\" : \"펌프 헤이즐넛\",      \"callingSeq\" : \"8707\",      \"payType\" : \"01\",      \"customGrp\" : \"R\",      \"btnStatus\" : \"D\",      \"markingName\" : \"H\",      \"markingSeq\" : \"8707\",      \"skuNameShort\" : \"헤이즐넛 시럽\"    } ]  }, {    \"categoryCode\" : \"C0000052\",    \"categoryName\" : \"카라멜 시럽\",    \"engCategoryName\" : \"\",    \"applyType1\" : \"01\",    \"applyType2\" : \"02\",    \"level\" : \"2\",    \"categoryDesc\" : \"\",    \"maxQty\" : \"9\",    \"maxQtyMsg\" : \"\",    \"stdRecipeFlag\" : \"N\",    \"payType\" : \"01\",    \"customGrp\" : \"R\",    \"btnStatus\" : \"D\",    \"skuList\" : [ {      \"skuNo\" : \"4002090000028\",      \"skuName\" : \"카라멜 시럽\",      \"baseQty\" : \"0\",      \"stdRecipeFlag\" : \"N\",      \"calories\" : \"0\",      \"price\" : \"600\",      \"callingName\" : \"펌프 카라멜\",      \"callingSeq\" : \"8703\",      \"payType\" : \"01\",      \"customGrp\" : \"R\",      \"btnStatus\" : \"D\",      \"markingName\" : \"C\",      \"markingSeq\" : \"8703\",      \"skuNameShort\" : \"카라멜 시럽\"    } ]  }, {    \"categoryCode\" : \"C0000055\",    \"categoryName\" : \"클래식 시럽\",    \"engCategoryName\" : \"\",    \"applyType1\" : \"01\",    \"applyType2\" : \"02\",    \"level\" : \"2\",    \"categoryDesc\" : \"\",    \"maxQty\" : \"9\",    \"maxQtyMsg\" : \"\",    \"stdRecipeFlag\" : \"Y\",    \"payType\" : \"01\",    \"customGrp\" : \"R\",    \"btnStatus\" : \"U\",    \"skuList\" : [ {      \"skuNo\" : \"4002090000071\",      \"skuName\" : \"클래식 시럽\",      \"baseQty\" : \"2\",      \"stdRecipeFlag\" : \"Y\",      \"calories\" : \"0\",      \"price\" : \"0\",      \"callingName\" : \"펌프 클래식 시럽\",      \"callingSeq\" : \"8701\",      \"payType\" : \"01\",      \"customGrp\" : \"R\",      \"btnStatus\" : \"U\",      \"markingName\" : \"CS\",      \"markingSeq\" : \"8701\",      \"skuNameShort\" : \"클래식 시럽\"    } ]  } ]}",
    "result_api_code": ""
}