{
    "result_code": "SUCCESS",
    "error_msg": "",
    "alert_msg": "",
    "location_href": "",
    "location_replace": "",
    "custom_script": "",
    "total_cnt": 0,
    "data": "{  \"gbn\" : \"C\",  \"menuList\" : [ {    \"delegateSku\" : {      \"hotYn\" : \"N\",      \"size\" : \"20\",      \"classCd\" : \"400110030\",      \"otherDelegateSku\" : \"9200000003509\",      \"skuNo\" : \"9200000003509\",      \"skuName\" : \"벨벳 다크 모카 나이트로\",      \"engSkuName\" : \"Velvet Dark Mocha Nitro\",      \"skuImgUrl\" : \"https://image.istarbucks.co.kr/skuImg/[9200000003509]_20210322093451621.jpg\",      \"hotIcedOnlyYn\" : \"Y\",      \"skuAttn\" : \"픽업대로 오시면 음료를 제조해드립니다\\r\\n시즌 원두로 추출 시 원두 특징에 맞게 즐길 수 있습니다.\"    },    \"hotSku\" : {      \"skuName\" : \"\",      \"engSkuName\" : \"\",      \"skuImgUrl\" : \"\",      \"prmtFlag\" : \"\",      \"personalFlag\" : \"\",      \"cupDcFlag\" : \"\",      \"menuType\" : \"\",      \"hotSkuList\" : [ ]    },    \"icedSku\" : {      \"skuName\" : \"벨벳 다크 모카 나이트로\",      \"engSkuName\" : \"Velvet Dark Mocha Nitro\",      \"skuImgUrl\" : \"https://image.istarbucks.co.kr/skuImg/[9200000003509]_20210322093451621.jpg\",      \"prmtFlag\" : \"N\",      \"personalFlag\" : \"Y\",      \"cupDcFlag\" : \"Y\",      \"menuType\" : \"R\",      \"icedSkuList\" : [ {        \"skuNo\" : \"9200000003509\",        \"size\" : \"20\",        \"sizeName\" : \"Tall\",        \"price\" : \"8500\",        \"shotQty\" : \"\"      }, {        \"skuNo\" : \"9200000003510\",        \"size\" : \"30\",        \"sizeName\" : \"Grande\",        \"price\" : \"9000\",        \"shotQty\" : \"\"      } ]    }  }, {    \"delegateSku\" : {      \"hotYn\" : \"N\",      \"size\" : \"20\",      \"classCd\" : \"400110030\",      \"otherDelegateSku\" : \"9200000002407\",      \"skuNo\" : \"9200000002407\",      \"skuName\" : \"리저브 나이트로\",      \"engSkuName\" : \"Reserve Nitro\",      \"skuImgUrl\" : \"https://image.istarbucks.co.kr/skuImg/[9200000002407]_20210222095926243.jpg\",      \"hotIcedOnlyYn\" : \"Y\",      \"skuAttn\" : \"픽업대로 오시면 음료를 제조해드립니다\\r\\n시즌 원두로 추출 시 원두 특징에 맞게 즐길 수 있습니다.\"    },    \"hotSku\" : {      \"skuName\" : \"\",      \"engSkuName\" : \"\",      \"skuImgUrl\" : \"\",      \"prmtFlag\" : \"\",      \"personalFlag\" : \"\",      \"cupDcFlag\" : \"\",      \"menuType\" : \"\",      \"hotSkuList\" : [ ]    },    \"icedSku\" : {      \"skuName\" : \"리저브 나이트로\",      \"engSkuName\" : \"Reserve Nitro\",      \"skuImgUrl\" : \"https://image.istarbucks.co.kr/skuImg/[9200000002407]_20210222095926243.jpg\",      \"prmtFlag\" : \"N\",      \"personalFlag\" : \"Y\",      \"cupDcFlag\" : \"Y\",      \"menuType\" : \"R\",      \"icedSkuList\" : [ {        \"skuNo\" : \"9200000002407\",        \"size\" : \"20\",        \"sizeName\" : \"Tall\",        \"price\" : \"7500\",        \"shotQty\" : \"\"      }, {        \"skuNo\" : \"9200000002408\",        \"size\" : \"30\",        \"sizeName\" : \"Grande\",        \"price\" : \"8000\",        \"shotQty\" : \"\"      } ]    }  }, {    \"delegateSku\" : {      \"hotYn\" : \"N\",      \"size\" : \"20\",      \"classCd\" : \"400110030\",      \"otherDelegateSku\" : \"9200000001636\",      \"skuNo\" : \"9200000001636\",      \"skuName\" : \"콜드 브루 몰트\",      \"engSkuName\" : \"Cold Brew Malt\",      \"skuImgUrl\" : \"https://image.istarbucks.co.kr/skuImg/[9200000001636]_20210222094734972.jpg\",      \"hotIcedOnlyYn\" : \"Y\",      \"skuAttn\" : \"리저브 매장에서만 주문 가능한 음료입니다.\"    },    \"hotSku\" : {      \"skuName\" : \"\",      \"engSkuName\" : \"\",      \"skuImgUrl\" : \"\",      \"prmtFlag\" : \"\",      \"personalFlag\" : \"\",      \"cupDcFlag\" : \"\",      \"menuType\" : \"\",      \"hotSkuList\" : [ ]    },    \"icedSku\" : {      \"skuName\" : \"콜드 브루 몰트\",      \"engSkuName\" : \"Cold Brew Malt\",      \"skuImgUrl\" : \"https://image.istarbucks.co.kr/skuImg/[9200000001636]_20210222094734972.jpg\",      \"prmtFlag\" : \"N\",      \"personalFlag\" : \"Y\",      \"cupDcFlag\" : \"Y\",      \"menuType\" : \"R\",      \"icedSkuList\" : [ {        \"skuNo\" : \"9200000001636\",        \"size\" : \"20\",        \"sizeName\" : \"Tall\",        \"price\" : \"8500\",        \"shotQty\" : \"\"      } ]    }  }, {    \"delegateSku\" : {      \"hotYn\" : \"N\",      \"size\" : \"20\",      \"classCd\" : \"400110030\",      \"otherDelegateSku\" : \"9200000001635\",      \"skuNo\" : \"9200000001635\",      \"skuName\" : \"콜드 브루 플로트\",      \"engSkuName\" : \"Cold Brew Float\",      \"skuImgUrl\" : \"https://image.istarbucks.co.kr/skuImg/[9200000001635]_20210222094702039.jpg\",      \"hotIcedOnlyYn\" : \"Y\",      \"skuAttn\" : \"리저브 매장에서만 주문 가능한 음료입니다.\"    },    \"hotSku\" : {      \"skuName\" : \"\",      \"engSkuName\" : \"\",      \"skuImgUrl\" : \"\",      \"prmtFlag\" : \"\",      \"personalFlag\" : \"\",      \"cupDcFlag\" : \"\",      \"menuType\" : \"\",      \"hotSkuList\" : [ ]    },    \"icedSku\" : {      \"skuName\" : \"콜드 브루 플로트\",      \"engSkuName\" : \"Cold Brew Float\",      \"skuImgUrl\" : \"https://image.istarbucks.co.kr/skuImg/[9200000001635]_20210222094702039.jpg\",      \"prmtFlag\" : \"N\",      \"personalFlag\" : \"Y\",      \"cupDcFlag\" : \"Y\",      \"menuType\" : \"R\",      \"icedSkuList\" : [ {        \"skuNo\" : \"9200000001635\",        \"size\" : \"20\",        \"sizeName\" : \"Tall\",        \"price\" : \"8000\",        \"shotQty\" : \"\"      } ]    }  }, {    \"delegateSku\" : {      \"hotYn\" : \"N\",      \"size\" : \"20\",      \"classCd\" : \"400110030\",      \"otherDelegateSku\" : \"9200000002093\",      \"skuNo\" : \"9200000002093\",      \"skuName\" : \"리저브 콜드 브루\",      \"engSkuName\" : \"Reserve Cold Brew\",      \"skuImgUrl\" : \"https://image.istarbucks.co.kr/skuImg/[9200000002093]_20210222095823366.jpg\",      \"hotIcedOnlyYn\" : \"Y\",      \"skuAttn\" : \"리저브 매장에서만 주문 가능한 음료입니다.\\r\\n\"    },    \"hotSku\" : {      \"skuName\" : \"\",      \"engSkuName\" : \"\",      \"skuImgUrl\" : \"\",      \"prmtFlag\" : \"\",      \"personalFlag\" : \"\",      \"cupDcFlag\" : \"\",      \"menuType\" : \"\",      \"hotSkuList\" : [ ]    },    \"icedSku\" : {      \"skuName\" : \"리저브 콜드 브루\",      \"engSkuName\" : \"Reserve Cold Brew\",      \"skuImgUrl\" : \"https://image.istarbucks.co.kr/skuImg/[9200000002093]_20210222095823366.jpg\",      \"prmtFlag\" : \"N\",      \"personalFlag\" : \"Y\",      \"cupDcFlag\" : \"Y\",      \"menuType\" : \"R\",      \"icedSkuList\" : [ {        \"skuNo\" : \"9200000002093\",        \"size\" : \"20\",        \"sizeName\" : \"Tall\",        \"price\" : \"6500\",        \"shotQty\" : \"\"      }, {        \"skuNo\" : \"9200000002094\",        \"size\" : \"30\",        \"sizeName\" : \"Grande\",        \"price\" : \"7000\",        \"shotQty\" : \"\"      } ]    }  }, {    \"delegateSku\" : {      \"hotYn\" : \"N\",      \"size\" : \"20\",      \"classCd\" : \"400110030\",      \"otherDelegateSku\" : \"9200000004005\",      \"skuNo\" : \"9200000004007\",      \"skuName\" : \"선 드라이드 콜롬비아 핀카 라 팔메라\",      \"engSkuName\" : \"Sun-Dried Colombia Finca La Palmera\",      \"skuImgUrl\" : \"https://image.istarbucks.co.kr/skuImg/[9200000004007]_20220323162238898.jpg\",      \"hotIcedOnlyYn\" : \"N\",      \"skuAttn\" : \"리저브 매장에서만 주문 가능한 음료입니다.\"    },    \"hotSku\" : {      \"skuName\" : \"선 드라이드 콜롬비아 핀카 라 팔메라\",      \"engSkuName\" : \"Sun-Dried Colombia Finca La Palmera\",      \"skuImgUrl\" : \"https://image.istarbucks.co.kr/skuImg/[9200000004005]_20220323161812439.jpg\",      \"prmtFlag\" : \"N\",      \"personalFlag\" : \"Y\",      \"cupDcFlag\" : \"Y\",      \"menuType\" : \"R\",      \"hotSkuList\" : [ {        \"skuNo\" : \"9200000004005\",        \"size\" : \"20\",        \"sizeName\" : \"Tall\",        \"price\" : \"10000\",        \"shotQty\" : \"\"      }, {        \"skuNo\" : \"9200000004006\",        \"size\" : \"30\",        \"sizeName\" : \"Grande\",        \"price\" : \"10500\",        \"shotQty\" : \"\"      } ]    },    \"icedSku\" : {      \"skuName\" : \"선 드라이드 콜롬비아 핀카 라 팔메라\",      \"engSkuName\" : \"Sun-Dried Colombia Finca La Palmera\",      \"skuImgUrl\" : \"https://image.istarbucks.co.kr/skuImg/[9200000004007]_20220323162238898.jpg\",      \"prmtFlag\" : \"N\",      \"personalFlag\" : \"Y\",      \"cupDcFlag\" : \"Y\",      \"menuType\" : \"R\",      \"icedSkuList\" : [ {        \"skuNo\" : \"9200000004007\",        \"size\" : \"20\",        \"sizeName\" : \"Tall\",        \"price\" : \"10000\",        \"shotQty\" : \"\"      }, {        \"skuNo\" : \"9200000004008\",        \"size\" : \"30\",        \"sizeName\" : \"Grande\",        \"price\" : \"10500\",        \"shotQty\" : \"\"      } ]    }  }, {    \"delegateSku\" : {      \"hotYn\" : \"N\",      \"size\" : \"20\",      \"classCd\" : \"400110030\",      \"otherDelegateSku\" : \"9200000004009\",      \"skuNo\" : \"9200000004011\",      \"skuName\" : \"선 드라이드 콜롬비아 핀카 라 팔메라\",      \"engSkuName\" : \"Sun-Dried Colombia Finca La Palmera\",      \"skuImgUrl\" : \"https://image.istarbucks.co.kr/skuImg/[9200000004011]_20220323162630531.jpg\",      \"hotIcedOnlyYn\" : \"N\",      \"skuAttn\" : \"리저브 매장에서만 주문 가능한 음료입니다.\"    },    \"hotSku\" : {      \"skuName\" : \"선 드라이드 콜롬비아 핀카 라 팔메라\",      \"engSkuName\" : \"Sun-Dried Colombia Finca La Palmera\",      \"skuImgUrl\" : \"https://image.istarbucks.co.kr/skuImg/[9200000004009]_20220323162505512.jpg\",      \"prmtFlag\" : \"N\",      \"personalFlag\" : \"Y\",      \"cupDcFlag\" : \"Y\",      \"menuType\" : \"R\",      \"hotSkuList\" : [ {        \"skuNo\" : \"9200000004009\",        \"size\" : \"20\",        \"sizeName\" : \"Tall\",        \"price\" : \"10000\",        \"shotQty\" : \"\"      }, {        \"skuNo\" : \"9200000004010\",        \"size\" : \"30\",        \"sizeName\" : \"Grande\",        \"price\" : \"10500\",        \"shotQty\" : \"\"      } ]    },    \"icedSku\" : {      \"skuName\" : \"선 드라이드 콜롬비아 핀카 라 팔메라\",      \"engSkuName\" : \"Sun-Dried Colombia Finca La Palmera\",      \"skuImgUrl\" : \"https://image.istarbucks.co.kr/skuImg/[9200000004011]_20220323162630531.jpg\",      \"prmtFlag\" : \"N\",      \"personalFlag\" : \"Y\",      \"cupDcFlag\" : \"Y\",      \"menuType\" : \"R\",      \"icedSkuList\" : [ {        \"skuNo\" : \"9200000004011\",        \"size\" : \"20\",        \"sizeName\" : \"Tall\",        \"price\" : \"10000\",        \"shotQty\" : \"\"      }, {        \"skuNo\" : \"9200000004012\",        \"size\" : \"30\",        \"sizeName\" : \"Grande\",        \"price\" : \"10500\",        \"shotQty\" : \"\"      } ]    }  }, {    \"delegateSku\" : {      \"hotYn\" : \"N\",      \"size\" : \"20\",      \"classCd\" : \"400110030\",      \"otherDelegateSku\" : \"9200000004013\",      \"skuNo\" : \"9200000004015\",      \"skuName\" : \"선 드라이드 콜롬비아 핀카 라 팔메라\",      \"engSkuName\" : \"Sun-Dried Colombia Finca La Palmera\",      \"skuImgUrl\" : \"https://image.istarbucks.co.kr/skuImg/[9200000004015]_20220323163015769.jpg\",      \"hotIcedOnlyYn\" : \"N\",      \"skuAttn\" : \"리저브 매장에서만 주문 가능한 음료입니다.\"    },    \"hotSku\" : {      \"skuName\" : \"선 드라이드 콜롬비아 핀카 라 팔메라\",      \"engSkuName\" : \"Sun-Dried Colombia Finca La Palmera\",      \"skuImgUrl\" : \"https://image.istarbucks.co.kr/skuImg/[9200000004013]_20220323162926047.jpg\",      \"prmtFlag\" : \"N\",      \"personalFlag\" : \"Y\",      \"cupDcFlag\" : \"Y\",      \"menuType\" : \"R\",      \"hotSkuList\" : [ {        \"skuNo\" : \"9200000004013\",        \"size\" : \"20\",        \"sizeName\" : \"Tall\",        \"price\" : \"10000\",        \"shotQty\" : \"\"      }, {        \"skuNo\" : \"9200000004014\",        \"size\" : \"30\",        \"sizeName\" : \"Grande\",        \"price\" : \"10500\",        \"shotQty\" : \"\"      } ]    },    \"icedSku\" : {      \"skuName\" : \"선 드라이드 콜롬비아 핀카 라 팔메라\",      \"engSkuName\" : \"Sun-Dried Colombia Finca La Palmera\",      \"skuImgUrl\" : \"https://image.istarbucks.co.kr/skuImg/[9200000004015]_20220323163015769.jpg\",      \"prmtFlag\" : \"N\",      \"personalFlag\" : \"Y\",      \"cupDcFlag\" : \"Y\",      \"menuType\" : \"R\",      \"icedSkuList\" : [ {        \"skuNo\" : \"9200000004015\",        \"size\" : \"20\",        \"sizeName\" : \"Tall\",        \"price\" : \"10000\",        \"shotQty\" : \"\"      }, {        \"skuNo\" : \"9200000004016\",        \"size\" : \"30\",        \"sizeName\" : \"Grande\",        \"price\" : \"10500\",        \"shotQty\" : \"\"      } ]    }  }, {    \"delegateSku\" : {      \"hotYn\" : \"N\",      \"size\" : \"20\",      \"classCd\" : \"400110030\",      \"otherDelegateSku\" : \"9200000004019\",      \"skuNo\" : \"9200000004021\",      \"skuName\" : \"인도네시아 웨스트 자바\",      \"engSkuName\" : \"Indonesia West Java\",      \"skuImgUrl\" : \"https://image.istarbucks.co.kr/skuImg/[9200000004021]_20220323165554216.jpg\",      \"hotIcedOnlyYn\" : \"N\",      \"skuAttn\" : \"리저브 매장에서만 주문 가능한 음료입니다.\"    },    \"hotSku\" : {      \"skuName\" : \"인도네시아 웨스트 자바\",      \"engSkuName\" : \"Indonesia West Java\",      \"skuImgUrl\" : \"https://image.istarbucks.co.kr/skuImg/[9200000004019]_20220323164859437.jpg\",      \"prmtFlag\" : \"N\",      \"personalFlag\" : \"Y\",      \"cupDcFlag\" : \"Y\",      \"menuType\" : \"R\",      \"hotSkuList\" : [ {        \"skuNo\" : \"9200000004019\",        \"size\" : \"20\",        \"sizeName\" : \"Tall\",        \"price\" : \"8000\",        \"shotQty\" : \"\"      }, {        \"skuNo\" : \"9200000004020\",        \"size\" : \"30\",        \"sizeName\" : \"Grande\",        \"price\" : \"8500\",        \"shotQty\" : \"\"      } ]    },    \"icedSku\" : {      \"skuName\" : \"인도네시아 웨스트 자바\",      \"engSkuName\" : \"Indonesia West Java\",      \"skuImgUrl\" : \"https://image.istarbucks.co.kr/skuImg/[9200000004021]_20220323165554216.jpg\",      \"prmtFlag\" : \"N\",      \"personalFlag\" : \"Y\",      \"cupDcFlag\" : \"Y\",      \"menuType\" : \"R\",      \"icedSkuList\" : [ {        \"skuNo\" : \"9200000004021\",        \"size\" : \"20\",        \"sizeName\" : \"Tall\",        \"price\" : \"8000\",        \"shotQty\" : \"\"      }, {        \"skuNo\" : \"9200000004022\",        \"size\" : \"30\",        \"sizeName\" : \"Grande\",        \"price\" : \"8500\",        \"shotQty\" : \"\"      } ]    }  }, {    \"delegateSku\" : {      \"hotYn\" : \"N\",      \"size\" : \"20\",      \"classCd\" : \"400110030\",      \"otherDelegateSku\" : \"9200000004023\",      \"skuNo\" : \"9200000004025\",      \"skuName\" : \"인도네시아 웨스트 자바\",      \"engSkuName\" : \"Indonesia West Java\",      \"skuImgUrl\" : \"https://image.istarbucks.co.kr/skuImg/[9200000004025]_20220323165857773.jpg\",      \"hotIcedOnlyYn\" : \"N\",      \"skuAttn\" : \"리저브 매장에서만 주문 가능한 음료입니다.\"    },    \"hotSku\" : {      \"skuName\" : \"인도네시아 웨스트 자바\",      \"engSkuName\" : \"Indonesia West Java\",      \"skuImgUrl\" : \"https://image.istarbucks.co.kr/skuImg/[9200000004023]_20220323165728732.jpg\",      \"prmtFlag\" : \"N\",      \"personalFlag\" : \"Y\",      \"cupDcFlag\" : \"Y\",      \"menuType\" : \"R\",      \"hotSkuList\" : [ {        \"skuNo\" : \"9200000004023\",        \"size\" : \"20\",        \"sizeName\" : \"Tall\",        \"price\" : \"8000\",        \"shotQty\" : \"\"      }, {        \"skuNo\" : \"9200000004024\",        \"size\" : \"30\",        \"sizeName\" : \"Grande\",        \"price\" : \"8500\",        \"shotQty\" : \"\"      } ]    },    \"icedSku\" : {      \"skuName\" : \"인도네시아 웨스트 자바\",      \"engSkuName\" : \"Indonesia West Java\",      \"skuImgUrl\" : \"https://image.istarbucks.co.kr/skuImg/[9200000004025]_20220323165857773.jpg\",      \"prmtFlag\" : \"N\",      \"personalFlag\" : \"Y\",      \"cupDcFlag\" : \"Y\",      \"menuType\" : \"R\",      \"icedSkuList\" : [ {        \"skuNo\" : \"9200000004025\",        \"size\" : \"20\",        \"sizeName\" : \"Tall\",        \"price\" : \"8000\",        \"shotQty\" : \"\"      }, {        \"skuNo\" : \"9200000004026\",        \"size\" : \"30\",        \"sizeName\" : \"Grande\",        \"price\" : \"8500\",        \"shotQty\" : \"\"      } ]    }  }, {    \"delegateSku\" : {      \"hotYn\" : \"N\",      \"size\" : \"20\",      \"classCd\" : \"400110030\",      \"otherDelegateSku\" : \"9200000004027\",      \"skuNo\" : \"9200000004029\",      \"skuName\" : \"인도네시아 웨스트 자바\",      \"engSkuName\" : \"Indonesia West Java\",      \"skuImgUrl\" : \"https://image.istarbucks.co.kr/skuImg/[9200000004029]_20220323171204596.jpg\",      \"hotIcedOnlyYn\" : \"N\",      \"skuAttn\" : \"리저브 매장에서만 주문 가능한 음료입니다.\"    },    \"hotSku\" : {      \"skuName\" : \"인도네시아 웨스트 자바\",      \"engSkuName\" : \"Indonesia West Java\",      \"skuImgUrl\" : \"https://image.istarbucks.co.kr/skuImg/[9200000004027]_20220323170823253.jpg\",      \"prmtFlag\" : \"N\",      \"personalFlag\" : \"Y\",      \"cupDcFlag\" : \"Y\",      \"menuType\" : \"R\",      \"hotSkuList\" : [ {        \"skuNo\" : \"9200000004027\",        \"size\" : \"20\",        \"sizeName\" : \"Tall\",        \"price\" : \"8000\",        \"shotQty\" : \"\"      }, {        \"skuNo\" : \"9200000004028\",        \"size\" : \"30\",        \"sizeName\" : \"Grande\",        \"price\" : \"8500\",        \"shotQty\" : \"\"      } ]    },    \"icedSku\" : {      \"skuName\" : \"인도네시아 웨스트 자바\",      \"engSkuName\" : \"Indonesia West Java\",      \"skuImgUrl\" : \"https://image.istarbucks.co.kr/skuImg/[9200000004029]_20220323171204596.jpg\",      \"prmtFlag\" : \"N\",      \"personalFlag\" : \"Y\",      \"cupDcFlag\" : \"Y\",      \"menuType\" : \"R\",      \"icedSkuList\" : [ {        \"skuNo\" : \"9200000004029\",        \"size\" : \"20\",        \"sizeName\" : \"Tall\",        \"price\" : \"8000\",        \"shotQty\" : \"\"      }, {        \"skuNo\" : \"9200000004030\",        \"size\" : \"30\",        \"sizeName\" : \"Grande\",        \"price\" : \"8500\",        \"shotQty\" : \"\"      } ]    }  }, {    \"delegateSku\" : {      \"hotYn\" : \"N\",      \"size\" : \"20\",      \"classCd\" : \"400110030\",      \"otherDelegateSku\" : \"9200000004033\",      \"skuNo\" : \"9200000004035\",      \"skuName\" : \"브라질 파젠다 카탄두바\",      \"engSkuName\" : \"Brazil Fazenda Catanduva\",      \"skuImgUrl\" : \"https://image.istarbucks.co.kr/skuImg/[9200000004035]_20220323172316136.jpg\",      \"hotIcedOnlyYn\" : \"N\",      \"skuAttn\" : \"리저브 매장에서만 주문 가능한 음료입니다.\"    },    \"hotSku\" : {      \"skuName\" : \"브라질 파젠다 카탄두바\",      \"engSkuName\" : \"Brazil Fazenda Catanduva\",      \"skuImgUrl\" : \"https://image.istarbucks.co.kr/skuImg/[9200000004033]_20220323172101718.jpg\",      \"prmtFlag\" : \"N\",      \"personalFlag\" : \"Y\",      \"cupDcFlag\" : \"Y\",      \"menuType\" : \"R\",      \"hotSkuList\" : [ {        \"skuNo\" : \"9200000004033\",        \"size\" : \"20\",        \"sizeName\" : \"Tall\",        \"price\" : \"7000\",        \"shotQty\" : \"\"      }, {        \"skuNo\" : \"9200000004034\",        \"size\" : \"30\",        \"sizeName\" : \"Grande\",        \"price\" : \"7500\",        \"shotQty\" : \"\"      } ]    },    \"icedSku\" : {      \"skuName\" : \"브라질 파젠다 카탄두바\",      \"engSkuName\" : \"Brazil Fazenda Catanduva\",      \"skuImgUrl\" : \"https://image.istarbucks.co.kr/skuImg/[9200000004035]_20220323172316136.jpg\",      \"prmtFlag\" : \"N\",      \"personalFlag\" : \"Y\",      \"cupDcFlag\" : \"Y\",      \"menuType\" : \"R\",      \"icedSkuList\" : [ {        \"skuNo\" : \"9200000004035\",        \"size\" : \"20\",        \"sizeName\" : \"Tall\",        \"price\" : \"7000\",        \"shotQty\" : \"\"      }, {        \"skuNo\" : \"9200000004036\",        \"size\" : \"30\",        \"sizeName\" : \"Grande\",        \"price\" : \"7500\",        \"shotQty\" : \"\"      } ]    }  }, {    \"delegateSku\" : {      \"hotYn\" : \"N\",      \"size\" : \"20\",      \"classCd\" : \"400110030\",      \"otherDelegateSku\" : \"9200000004037\",      \"skuNo\" : \"9200000004039\",      \"skuName\" : \"브라질 파젠다 카탄두바\",      \"engSkuName\" : \"Brazil Fazenda Catanduva\",      \"skuImgUrl\" : \"https://image.istarbucks.co.kr/skuImg/[9200000004039]_20220323172523350.jpg\",      \"hotIcedOnlyYn\" : \"N\",      \"skuAttn\" : \"리저브 매장에서만 주문 가능한 음료입니다.\"    },    \"hotSku\" : {      \"skuName\" : \"브라질 파젠다 카탄두바\",      \"engSkuName\" : \"Brazil Fazenda Catanduva\",      \"skuImgUrl\" : \"https://image.istarbucks.co.kr/skuImg/[9200000004037]_20220323172412544.jpg\",      \"prmtFlag\" : \"N\",      \"personalFlag\" : \"Y\",      \"cupDcFlag\" : \"Y\",      \"menuType\" : \"R\",      \"hotSkuList\" : [ {        \"skuNo\" : \"9200000004037\",        \"size\" : \"20\",        \"sizeName\" : \"Tall\",        \"price\" : \"7000\",        \"shotQty\" : \"\"      }, {        \"skuNo\" : \"9200000004038\",        \"size\" : \"30\",        \"sizeName\" : \"Grande\",        \"price\" : \"7500\",        \"shotQty\" : \"\"      } ]    },    \"icedSku\" : {      \"skuName\" : \"브라질 파젠다 카탄두바\",      \"engSkuName\" : \"Brazil Fazenda Catanduva\",      \"skuImgUrl\" : \"https://image.istarbucks.co.kr/skuImg/[9200000004039]_20220323172523350.jpg\",      \"prmtFlag\" : \"N\",      \"personalFlag\" : \"Y\",      \"cupDcFlag\" : \"Y\",      \"menuType\" : \"R\",      \"icedSkuList\" : [ {        \"skuNo\" : \"9200000004039\",        \"size\" : \"20\",        \"sizeName\" : \"Tall\",        \"price\" : \"7000\",        \"shotQty\" : \"\"      }, {        \"skuNo\" : \"9200000004040\",        \"size\" : \"30\",        \"sizeName\" : \"Grande\",        \"price\" : \"7500\",        \"shotQty\" : \"\"      } ]    }  }, {    \"delegateSku\" : {      \"hotYn\" : \"N\",      \"size\" : \"20\",      \"classCd\" : \"400110030\",      \"otherDelegateSku\" : \"9200000004041\",      \"skuNo\" : \"9200000004043\",      \"skuName\" : \"브라질 파젠다 카탄두바\",      \"engSkuName\" : \"Brazil Fazenda Catanduva\",      \"skuImgUrl\" : \"https://image.istarbucks.co.kr/skuImg/[9200000004043]_20220323172743956.jpg\",      \"hotIcedOnlyYn\" : \"N\",      \"skuAttn\" : \"리저브 매장에서만 주문 가능한 음료입니다.\"    },    \"hotSku\" : {      \"skuName\" : \"브라질 파젠다 카탄두바\",      \"engSkuName\" : \"Brazil Fazenda Catanduva\",      \"skuImgUrl\" : \"https://image.istarbucks.co.kr/skuImg/[9200000004041]_20220323172654364.jpg\",      \"prmtFlag\" : \"N\",      \"personalFlag\" : \"Y\",      \"cupDcFlag\" : \"Y\",      \"menuType\" : \"R\",      \"hotSkuList\" : [ {        \"skuNo\" : \"9200000004041\",        \"size\" : \"20\",        \"sizeName\" : \"Tall\",        \"price\" : \"7000\",        \"shotQty\" : \"\"      }, {        \"skuNo\" : \"9200000004042\",        \"size\" : \"30\",        \"sizeName\" : \"Grande\",        \"price\" : \"7500\",        \"shotQty\" : \"\"      } ]    },    \"icedSku\" : {      \"skuName\" : \"브라질 파젠다 카탄두바\",      \"engSkuName\" : \"Brazil Fazenda Catanduva\",      \"skuImgUrl\" : \"https://image.istarbucks.co.kr/skuImg/[9200000004043]_20220323172743956.jpg\",      \"prmtFlag\" : \"N\",      \"personalFlag\" : \"Y\",      \"cupDcFlag\" : \"Y\",      \"menuType\" : \"R\",      \"icedSkuList\" : [ {        \"skuNo\" : \"9200000004043\",        \"size\" : \"20\",        \"sizeName\" : \"Tall\",        \"price\" : \"7000\",        \"shotQty\" : \"\"      }, {        \"skuNo\" : \"9200000004044\",        \"size\" : \"30\",        \"sizeName\" : \"Grande\",        \"price\" : \"7500\",        \"shotQty\" : \"\"      } ]    }  }, {    \"delegateSku\" : {      \"hotYn\" : \"N\",      \"size\" : \"20\",      \"classCd\" : \"400110030\",      \"otherDelegateSku\" : \"9200000003927\",      \"skuNo\" : \"9200000003929\",      \"skuName\" : \"니카라과 마라카투라\",      \"engSkuName\" : \"Nicaragua Maracaturra\",      \"skuImgUrl\" : \"https://image.istarbucks.co.kr/skuImg/[9200000003929]_20220125101228491.jpg\",      \"hotIcedOnlyYn\" : \"N\",      \"skuAttn\" : \"리저브 매장에서만 주문 가능한 음료입니다.\"    },    \"hotSku\" : {      \"skuName\" : \"니카라과 마라카투라\",      \"engSkuName\" : \"Nicaragua Maracaturra\",      \"skuImgUrl\" : \"https://image.istarbucks.co.kr/skuImg/[9200000003927]_20220125101151158.jpg\",      \"prmtFlag\" : \"N\",      \"personalFlag\" : \"Y\",      \"cupDcFlag\" : \"Y\",      \"menuType\" : \"R\",      \"hotSkuList\" : [ {        \"skuNo\" : \"9200000003927\",        \"size\" : \"20\",        \"sizeName\" : \"Tall\",        \"price\" : \"10000\",        \"shotQty\" : \"\"      }, {        \"skuNo\" : \"9200000003928\",        \"size\" : \"30\",        \"sizeName\" : \"Grande\",        \"price\" : \"10500\",        \"shotQty\" : \"\"      } ]    },    \"icedSku\" : {      \"skuName\" : \"니카라과 마라카투라\",      \"engSkuName\" : \"Nicaragua Maracaturra\",      \"skuImgUrl\" : \"https://image.istarbucks.co.kr/skuImg/[9200000003929]_20220125101228491.jpg\",      \"prmtFlag\" : \"N\",      \"personalFlag\" : \"Y\",      \"cupDcFlag\" : \"Y\",      \"menuType\" : \"R\",      \"icedSkuList\" : [ {        \"skuNo\" : \"9200000003929\",        \"size\" : \"20\",        \"sizeName\" : \"Tall\",        \"price\" : \"10000\",        \"shotQty\" : \"\"      }, {        \"skuNo\" : \"9200000003930\",        \"size\" : \"30\",        \"sizeName\" : \"Grande\",        \"price\" : \"10500\",        \"shotQty\" : \"\"      } ]    }  }, {    \"delegateSku\" : {      \"hotYn\" : \"N\",      \"size\" : \"20\",      \"classCd\" : \"400110030\",      \"otherDelegateSku\" : \"9200000003931\",      \"skuNo\" : \"9200000003933\",      \"skuName\" : \"니카라과 마라카투라\",      \"engSkuName\" : \"Nicaragua Maracaturra\",      \"skuImgUrl\" : \"https://image.istarbucks.co.kr/skuImg/[9200000003933]_20220125101554974.jpg\",      \"hotIcedOnlyYn\" : \"N\",      \"skuAttn\" : \"리저브 매장에서만 주문 가능한 음료입니다.\"    },    \"hotSku\" : {      \"skuName\" : \"니카라과 마라카투라\",      \"engSkuName\" : \"Nicaragua Maracaturra\",      \"skuImgUrl\" : \"https://image.istarbucks.co.kr/skuImg/[9200000003931]_20220125101517751.jpg\",      \"prmtFlag\" : \"N\",      \"personalFlag\" : \"Y\",      \"cupDcFlag\" : \"Y\",      \"menuType\" : \"R\",      \"hotSkuList\" : [ {        \"skuNo\" : \"9200000003931\",        \"size\" : \"20\",        \"sizeName\" : \"Tall\",        \"price\" : \"10000\",        \"shotQty\" : \"\"      }, {        \"skuNo\" : \"9200000003932\",        \"size\" : \"30\",        \"sizeName\" : \"Grande\",        \"price\" : \"10500\",        \"shotQty\" : \"\"      } ]    },    \"icedSku\" : {      \"skuName\" : \"니카라과 마라카투라\",      \"engSkuName\" : \"Nicaragua Maracaturra\",      \"skuImgUrl\" : \"https://image.istarbucks.co.kr/skuImg/[9200000003933]_20220125101554974.jpg\",      \"prmtFlag\" : \"N\",      \"personalFlag\" : \"Y\",      \"cupDcFlag\" : \"Y\",      \"menuType\" : \"R\",      \"icedSkuList\" : [ {        \"skuNo\" : \"9200000003933\",        \"size\" : \"20\",        \"sizeName\" : \"Tall\",        \"price\" : \"10000\",        \"shotQty\" : \"\"      }, {        \"skuNo\" : \"9200000003934\",        \"size\" : \"30\",        \"sizeName\" : \"Grande\",        \"price\" : \"10500\",        \"shotQty\" : \"\"      } ]    }  }, {    \"delegateSku\" : {      \"hotYn\" : \"N\",      \"size\" : \"20\",      \"classCd\" : \"400110030\",      \"otherDelegateSku\" : \"9200000003935\",      \"skuNo\" : \"9200000003937\",      \"skuName\" : \"니카라과 마라카투라\",      \"engSkuName\" : \"Nicaragua Maracaturra\",      \"skuImgUrl\" : \"https://image.istarbucks.co.kr/skuImg/[9200000003937]_20220125101707925.jpg\",      \"hotIcedOnlyYn\" : \"N\",      \"skuAttn\" : \"리저브 매장에서만 주문 가능한 음료입니다.\"    },    \"hotSku\" : {      \"skuName\" : \"니카라과 마라카투라\",      \"engSkuName\" : \"Nicaragua Maracaturra\",      \"skuImgUrl\" : \"https://image.istarbucks.co.kr/skuImg/[9200000003935]_20220125101632721.jpg\",      \"prmtFlag\" : \"N\",      \"personalFlag\" : \"Y\",      \"cupDcFlag\" : \"Y\",      \"menuType\" : \"R\",      \"hotSkuList\" : [ {        \"skuNo\" : \"9200000003935\",        \"size\" : \"20\",        \"sizeName\" : \"Tall\",        \"price\" : \"10000\",        \"shotQty\" : \"\"      }, {        \"skuNo\" : \"9200000003936\",        \"size\" : \"30\",        \"sizeName\" : \"Grande\",        \"price\" : \"10500\",        \"shotQty\" : \"\"      } ]    },    \"icedSku\" : {      \"skuName\" : \"니카라과 마라카투라\",      \"engSkuName\" : \"Nicaragua Maracaturra\",      \"skuImgUrl\" : \"https://image.istarbucks.co.kr/skuImg/[9200000003937]_20220125101707925.jpg\",      \"prmtFlag\" : \"N\",      \"personalFlag\" : \"Y\",      \"cupDcFlag\" : \"Y\",      \"menuType\" : \"R\",      \"icedSkuList\" : [ {        \"skuNo\" : \"9200000003937\",        \"size\" : \"20\",        \"sizeName\" : \"Tall\",        \"price\" : \"10000\",        \"shotQty\" : \"\"      }, {        \"skuNo\" : \"9200000003938\",        \"size\" : \"30\",        \"sizeName\" : \"Grande\",        \"price\" : \"10500\",        \"shotQty\" : \"\"      } ]    }  }, {    \"delegateSku\" : {      \"hotYn\" : \"N\",      \"size\" : \"20\",      \"classCd\" : \"400110030\",      \"otherDelegateSku\" : \"9200000003913\",      \"skuNo\" : \"9200000003915\",      \"skuName\" : \"선 드라이드 에티오피아 게라 팜\",      \"engSkuName\" : \"Sun-Dried Ethiopia Gera Farm\",      \"skuImgUrl\" : \"https://image.istarbucks.co.kr/skuImg/[9200000003915]_20220125100448162.jpg\",      \"hotIcedOnlyYn\" : \"N\",      \"skuAttn\" : \"리저브 매장에서만 주문 가능한 음료입니다.\"    },    \"hotSku\" : {      \"skuName\" : \"선 드라이드 에티오피아 게라 팜\",      \"engSkuName\" : \"Sun-Dried Ethiopia Gera Farm\",      \"skuImgUrl\" : \"https://image.istarbucks.co.kr/skuImg/[9200000003913]_20220125100330259.jpg\",      \"prmtFlag\" : \"N\",      \"personalFlag\" : \"Y\",      \"cupDcFlag\" : \"Y\",      \"menuType\" : \"R\",      \"hotSkuList\" : [ {        \"skuNo\" : \"9200000003913\",        \"size\" : \"20\",        \"sizeName\" : \"Tall\",        \"price\" : \"8000\",        \"shotQty\" : \"\"      }, {        \"skuNo\" : \"9200000003914\",        \"size\" : \"30\",        \"sizeName\" : \"Grande\",        \"price\" : \"8500\",        \"shotQty\" : \"\"      } ]    },    \"icedSku\" : {      \"skuName\" : \"선 드라이드 에티오피아 게라 팜\",      \"engSkuName\" : \"Sun-Dried Ethiopia Gera Farm\",      \"skuImgUrl\" : \"https://image.istarbucks.co.kr/skuImg/[9200000003915]_20220125100448162.jpg\",      \"prmtFlag\" : \"N\",      \"personalFlag\" : \"Y\",      \"cupDcFlag\" : \"Y\",      \"menuType\" : \"R\",      \"icedSkuList\" : [ {        \"skuNo\" : \"9200000003915\",        \"size\" : \"20\",        \"sizeName\" : \"Tall\",        \"price\" : \"8000\",        \"shotQty\" : \"\"      }, {        \"skuNo\" : \"9200000003916\",        \"size\" : \"30\",        \"sizeName\" : \"Grande\",        \"price\" : \"8500\",        \"shotQty\" : \"\"      } ]    }  }, {    \"delegateSku\" : {      \"hotYn\" : \"N\",      \"size\" : \"20\",      \"classCd\" : \"400110030\",      \"otherDelegateSku\" : \"9200000003917\",      \"skuNo\" : \"9200000003919\",      \"skuName\" : \"선 드라이드 에티오피아 게라 팜\",      \"engSkuName\" : \"Sun-Dried Ethiopia Gera Farm\",      \"skuImgUrl\" : \"https://image.istarbucks.co.kr/skuImg/[9200000003919]_20220125100642948.jpg\",      \"hotIcedOnlyYn\" : \"N\",      \"skuAttn\" : \"리저브 매장에서만 주문 가능한 음료입니다.\"    },    \"hotSku\" : {      \"skuName\" : \"선 드라이드 에티오피아 게라 팜\",      \"engSkuName\" : \"Sun-Dried Ethiopia Gera Farm\",      \"skuImgUrl\" : \"https://image.istarbucks.co.kr/skuImg/[9200000003917]_20220125100600883.jpg\",      \"prmtFlag\" : \"N\",      \"personalFlag\" : \"Y\",      \"cupDcFlag\" : \"Y\",      \"menuType\" : \"R\",      \"hotSkuList\" : [ {        \"skuNo\" : \"9200000003917\",        \"size\" : \"20\",        \"sizeName\" : \"Tall\",        \"price\" : \"8000\",        \"shotQty\" : \"\"      }, {        \"skuNo\" : \"9200000003918\",        \"size\" : \"30\",        \"sizeName\" : \"Grande\",        \"price\" : \"8500\",        \"shotQty\" : \"\"      } ]    },    \"icedSku\" : {      \"skuName\" : \"선 드라이드 에티오피아 게라 팜\",      \"engSkuName\" : \"Sun-Dried Ethiopia Gera Farm\",      \"skuImgUrl\" : \"https://image.istarbucks.co.kr/skuImg/[9200000003919]_20220125100642948.jpg\",      \"prmtFlag\" : \"N\",      \"personalFlag\" : \"Y\",      \"cupDcFlag\" : \"Y\",      \"menuType\" : \"R\",      \"icedSkuList\" : [ {        \"skuNo\" : \"9200000003919\",        \"size\" : \"20\",        \"sizeName\" : \"Tall\",        \"price\" : \"8000\",        \"shotQty\" : \"\"      }, {        \"skuNo\" : \"9200000003920\",        \"size\" : \"30\",        \"sizeName\" : \"Grande\",        \"price\" : \"8500\",        \"shotQty\" : \"\"      } ]    }  }, {    \"delegateSku\" : {      \"hotYn\" : \"N\",      \"size\" : \"20\",      \"classCd\" : \"400110030\",      \"otherDelegateSku\" : \"9200000003921\",      \"skuNo\" : \"9200000003923\",      \"skuName\" : \"선 드라이드 에티오피아 게라 팜\",      \"engSkuName\" : \"Sun-Dried Ethiopia Gera Farm\",      \"skuImgUrl\" : \"https://image.istarbucks.co.kr/skuImg/[9200000003923]_20220125100941087.jpg\",      \"hotIcedOnlyYn\" : \"N\",      \"skuAttn\" : \"리저브 매장에서만 주문 가능한 음료입니다.\"    },    \"hotSku\" : {      \"skuName\" : \"선 드라이드 에티오피아 게라 팜\",      \"engSkuName\" : \"Sun-Dried Ethiopia Gera Farm\",      \"skuImgUrl\" : \"https://image.istarbucks.co.kr/skuImg/[9200000003921]_20220125100849608.jpg\",      \"prmtFlag\" : \"N\",      \"personalFlag\" : \"Y\",      \"cupDcFlag\" : \"Y\",      \"menuType\" : \"R\",      \"hotSkuList\" : [ {        \"skuNo\" : \"9200000003921\",        \"size\" : \"20\",        \"sizeName\" : \"Tall\",        \"price\" : \"8000\",        \"shotQty\" : \"\"      }, {        \"skuNo\" : \"9200000003922\",        \"size\" : \"30\",        \"sizeName\" : \"Grande\",        \"price\" : \"8500\",        \"shotQty\" : \"\"      } ]    },    \"icedSku\" : {      \"skuName\" : \"선 드라이드 에티오피아 게라 팜\",      \"engSkuName\" : \"Sun-Dried Ethiopia Gera Farm\",      \"skuImgUrl\" : \"https://image.istarbucks.co.kr/skuImg/[9200000003923]_20220125100941087.jpg\",      \"prmtFlag\" : \"N\",      \"personalFlag\" : \"Y\",      \"cupDcFlag\" : \"Y\",      \"menuType\" : \"R\",      \"icedSkuList\" : [ {        \"skuNo\" : \"9200000003923\",        \"size\" : \"20\",        \"sizeName\" : \"Tall\",        \"price\" : \"8000\",        \"shotQty\" : \"\"      }, {        \"skuNo\" : \"9200000003924\",        \"size\" : \"30\",        \"sizeName\" : \"Grande\",        \"price\" : \"8500\",        \"shotQty\" : \"\"      } ]    }  }, {    \"delegateSku\" : {      \"hotYn\" : \"N\",      \"size\" : \"20\",      \"classCd\" : \"400110030\",      \"otherDelegateSku\" : \"9200000003941\",      \"skuNo\" : \"9200000003943\",      \"skuName\" : \"과테말라 산타 클라라 에스테이트\",      \"engSkuName\" : \"Guatemala Santa Clara Estate\",      \"skuImgUrl\" : \"https://image.istarbucks.co.kr/skuImg/[9200000003943]_20220125101911599.jpg\",      \"hotIcedOnlyYn\" : \"N\",      \"skuAttn\" : \"리저브 매장에서만 주문 가능한 음료입니다.\"    },    \"hotSku\" : {      \"skuName\" : \"과테말라 산타 클라라 에스테이트\",      \"engSkuName\" : \"Guatemala Santa Clara Estate\",      \"skuImgUrl\" : \"https://image.istarbucks.co.kr/skuImg/[9200000003941]_20220125101828611.jpg\",      \"prmtFlag\" : \"N\",      \"personalFlag\" : \"Y\",      \"cupDcFlag\" : \"Y\",      \"menuType\" : \"R\",      \"hotSkuList\" : [ {        \"skuNo\" : \"9200000003941\",        \"size\" : \"20\",        \"sizeName\" : \"Tall\",        \"price\" : \"8000\",        \"shotQty\" : \"\"      }, {        \"skuNo\" : \"9200000003942\",        \"size\" : \"30\",        \"sizeName\" : \"Grande\",        \"price\" : \"8500\",        \"shotQty\" : \"\"      } ]    },    \"icedSku\" : {      \"skuName\" : \"과테말라 산타 클라라 에스테이트\",      \"engSkuName\" : \"Guatemala Santa Clara Estate\",      \"skuImgUrl\" : \"https://image.istarbucks.co.kr/skuImg/[9200000003943]_20220125101911599.jpg\",      \"prmtFlag\" : \"N\",      \"personalFlag\" : \"Y\",      \"cupDcFlag\" : \"Y\",      \"menuType\" : \"R\",      \"icedSkuList\" : [ {        \"skuNo\" : \"9200000003943\",        \"size\" : \"20\",        \"sizeName\" : \"Tall\",        \"price\" : \"8000\",        \"shotQty\" : \"\"      }, {        \"skuNo\" : \"9200000003944\",        \"size\" : \"30\",        \"sizeName\" : \"Grande\",        \"price\" : \"8500\",        \"shotQty\" : \"\"      } ]    }  }, {    \"delegateSku\" : {      \"hotYn\" : \"N\",      \"size\" : \"20\",      \"classCd\" : \"400110030\",      \"otherDelegateSku\" : \"9200000003945\",      \"skuNo\" : \"9200000003947\",      \"skuName\" : \"과테말라 산타 클라라 에스테이트\",      \"engSkuName\" : \"Guatemala Santa Clara Estate\",      \"skuImgUrl\" : \"https://image.istarbucks.co.kr/skuImg/[9200000003947]_20220125102251550.jpg\",      \"hotIcedOnlyYn\" : \"N\",      \"skuAttn\" : \"리저브 매장에서만 주문 가능한 음료입니다.\"    },    \"hotSku\" : {      \"skuName\" : \"과테말라 산타 클라라 에스테이트\",      \"engSkuName\" : \"Guatemala Santa Clara Estate\",      \"skuImgUrl\" : \"https://image.istarbucks.co.kr/skuImg/[9200000003945]_20220125101947815.jpg\",      \"prmtFlag\" : \"N\",      \"personalFlag\" : \"Y\",      \"cupDcFlag\" : \"Y\",      \"menuType\" : \"R\",      \"hotSkuList\" : [ {        \"skuNo\" : \"9200000003945\",        \"size\" : \"20\",        \"sizeName\" : \"Tall\",        \"price\" : \"8000\",        \"shotQty\" : \"\"      }, {        \"skuNo\" : \"9200000003946\",        \"size\" : \"30\",        \"sizeName\" : \"Grande\",        \"price\" : \"8500\",        \"shotQty\" : \"\"      } ]    },    \"icedSku\" : {      \"skuName\" : \"과테말라 산타 클라라 에스테이트\",      \"engSkuName\" : \"Guatemala Santa Clara Estate\",      \"skuImgUrl\" : \"https://image.istarbucks.co.kr/skuImg/[9200000003947]_20220125102251550.jpg\",      \"prmtFlag\" : \"N\",      \"personalFlag\" : \"Y\",      \"cupDcFlag\" : \"Y\",      \"menuType\" : \"R\",      \"icedSkuList\" : [ {        \"skuNo\" : \"9200000003947\",        \"size\" : \"20\",        \"sizeName\" : \"Tall\",        \"price\" : \"8000\",        \"shotQty\" : \"\"      }, {        \"skuNo\" : \"9200000003948\",        \"size\" : \"30\",        \"sizeName\" : \"Grande\",        \"price\" : \"8500\",        \"shotQty\" : \"\"      } ]    }  }, {    \"delegateSku\" : {      \"hotYn\" : \"N\",      \"size\" : \"20\",      \"classCd\" : \"400110030\",      \"otherDelegateSku\" : \"9200000003951\",      \"skuNo\" : \"9200000003951\",      \"skuName\" : \"과테말라 산타 클라라 에스테이트\",      \"engSkuName\" : \"Guatemala Santa Clara Estate\",      \"skuImgUrl\" : \"https://image.istarbucks.co.kr/skuImg/[9200000003951]_20220125102813215.jpg\",      \"hotIcedOnlyYn\" : \"N\",      \"skuAttn\" : \"리저브 매장에서만 주문 가능한 음료입니다.\"    },    \"hotSku\" : {      \"skuName\" : \"과테말라 산타 클라라 에스테이트\",      \"engSkuName\" : \"Guatemala Santa Clara Estate\",      \"skuImgUrl\" : \"https://image.istarbucks.co.kr/skuImg/[9200000003949]_20220125102639791.jpg\",      \"prmtFlag\" : \"N\",      \"personalFlag\" : \"Y\",      \"cupDcFlag\" : \"Y\",      \"menuType\" : \"R\",      \"hotSkuList\" : [ {        \"skuNo\" : \"9200000003949\",        \"size\" : \"20\",        \"sizeName\" : \"Tall\",        \"price\" : \"8000\",        \"shotQty\" : \"\"      }, {        \"skuNo\" : \"9200000003950\",        \"size\" : \"30\",        \"sizeName\" : \"Grande\",        \"price\" : \"8500\",        \"shotQty\" : \"\"      } ]    },    \"icedSku\" : {      \"skuName\" : \"과테말라 산타 클라라 에스테이트\",      \"engSkuName\" : \"Guatemala Santa Clara Estate\",      \"skuImgUrl\" : \"https://image.istarbucks.co.kr/skuImg/[9200000003951]_20220125102813215.jpg\",      \"prmtFlag\" : \"N\",      \"personalFlag\" : \"Y\",      \"cupDcFlag\" : \"Y\",      \"menuType\" : \"R\",      \"icedSkuList\" : [ {        \"skuNo\" : \"9200000003951\",        \"size\" : \"20\",        \"sizeName\" : \"Tall\",        \"price\" : \"8000\",        \"shotQty\" : \"\"      }, {        \"skuNo\" : \"9200000003952\",        \"size\" : \"30\",        \"sizeName\" : \"Grande\",        \"price\" : \"8500\",        \"shotQty\" : \"\"      } ]    }  } ]}",
    "result_api_code": ""
}